{
  "inputs": [
    { "name": "a", "dtype": "F32", "shape": ["_"] },
    { "name": "b", "dtype": "F32", "shape": ["_"] },
    { "name": "t", "dtype": "F32", "shape": ["_"] }
  ],
  "outputs": [
    { "name": "output", "dtype": "F32", "shape": ["_"] }
  ],
  "nodes": [
    { "id": "diff", "op": "Sub" },
    { "id": "delta", "op": "Mul" },
    { "id": "res", "op": "Add" }
  ],
  "links": [
    ["b", "diff.left"],
    ["a", "diff.right"],
    ["diff.output", "delta.left"],
    ["t", "delta.right"],
    ["a", "res.left"],
    ["delta.output", "res.right"],
    ["res.output", "output"]
  ]
}
